repairwheel/__init__.py
repairwheel/__main__.py
repairwheel/compat.py
repairwheel/fileutil.py
repairwheel/py.typed
repairwheel/repair.py
repairwheel/wheel.py
repairwheel/_vendor/__init__.py
repairwheel/_vendor/auditwheel.pyi
repairwheel/_vendor/vendor.txt
repairwheel/_vendor/auditwheel/LICENSE
repairwheel/_vendor/auditwheel/LICENSE.txt
repairwheel/_vendor/auditwheel/__init__.py
repairwheel/_vendor/auditwheel/__main__.py
repairwheel/_vendor/auditwheel/condatools.py
repairwheel/_vendor/auditwheel/elfutils.py
repairwheel/_vendor/auditwheel/error.py
repairwheel/_vendor/auditwheel/genericpkgctx.py
repairwheel/_vendor/auditwheel/hashfile.py
repairwheel/_vendor/auditwheel/lddtree.py
repairwheel/_vendor/auditwheel/libc.py
repairwheel/_vendor/auditwheel/main.py
repairwheel/_vendor/auditwheel/main_lddtree.py
repairwheel/_vendor/auditwheel/main_repair.py
repairwheel/_vendor/auditwheel/main_show.py
repairwheel/_vendor/auditwheel/musllinux.py
repairwheel/_vendor/auditwheel/patcher.py
repairwheel/_vendor/auditwheel/repair.py
repairwheel/_vendor/auditwheel/tmpdirs.py
repairwheel/_vendor/auditwheel/tools.py
repairwheel/_vendor/auditwheel/wheel_abi.py
repairwheel/_vendor/auditwheel/wheeltools.py
repairwheel/_vendor/auditwheel/_vendor/__init__.py
repairwheel/_vendor/auditwheel/_vendor/wheel/LICENSE.txt
repairwheel/_vendor/auditwheel/_vendor/wheel/__init__.py
repairwheel/_vendor/auditwheel/_vendor/wheel/pkginfo.py
repairwheel/_vendor/auditwheel/policy/__init__.py
repairwheel/_vendor/auditwheel/policy/manylinux-policy.json
repairwheel/_vendor/auditwheel/policy/musllinux-policy.json
repairwheel/_vendor/auditwheel/policy/policy-schema.json
repairwheel/_vendor/delocate/LICENSE
repairwheel/_vendor/delocate/__init__.py
repairwheel/_vendor/delocate/_version.py
repairwheel/_vendor/delocate/delocating.py
repairwheel/_vendor/delocate/fuse.py
repairwheel/_vendor/delocate/libsana.py
repairwheel/_vendor/delocate/pkginfo.py
repairwheel/_vendor/delocate/py.typed
repairwheel-0.3.2.dist-info/METADATA
repairwheel-0.3.2.dist-info/WHEEL
repairwheel-0.3.2.dist-info/entry_points.txt
repairwheel-0.3.2.dist-info/licenses/LICENSE
repairwheel-0.3.2.dist-info/RECORD
